<?xml version="1.0" encoding="utf-8"?>
<openerp>
    <data>
        <record id="product_template_only_form_view_price_attribute" model="ir.ui.view">
            <field name="name">product.template.product.form.price.attribute</field>
            <field name="model">product.template</field>
            <field name="inherit_id" ref="product.product_template_only_form_view"/>
            <field name="arch" type="xml">
                <xpath expr="//field[@name='attribute_id']" position="after">
                    <field name="price_extra"/>
                    <field name="cost_extra"/>
                </xpath>
            </field>
        </record>
        <record model="ir.ui.view" id="sale_order_extended_form_view">
            <field name="name">sale.order.extended.form</field>
            <field name="model">sale.order</field>
            <field name="inherit_id" ref="sale_product_variants.sale_order_extended_form_view" />
            <field name="arch" type="xml">
                <xpath expr="//button[@name='update_price_unit']" position="replace">
                </xpath>
            </field>
        </record>
        <record id="view_order_form_recalculate_price" model="ir.ui.view">
            <field name="name">sale.order.form</field>
            <field name="model">sale.order</field>
            <field name="inherit_id" ref="sale.view_order_form"/>
            <field name="arch" type="xml">
                <field name="pricelist_id" position="after">
                    <button name="recalculate_prices" string="(Recalculate prices)" type="object" colspan="4" class="oe_link"/>
                </field>
            </field>
        </record>
     </data>
</openerp>
