<?xml version="1.0" encoding="utf-8"?>
<openerp>
    <data>

        <record id="view_account_analytic_account_form_sal" model="ir.ui.view">
            <field name="name">account.analytic.account.inherit.sal</field>
            <field name="model">account.analytic.account</field>
            <field name="inherit_id" ref="analytic.view_account_analytic_account_form"/>
            <field name="priority" eval="9999"/>
            <field name="arch" type="xml">
                <group name='main' position="after">
                    <separator string="Use SAL"
                           attrs="{'invisible': [('use_sal','!=',True)]}"
                           />
                    <div>
                        <field name="use_sal" class="oe_inline"/>
                        <label for="use_sal" />
                        <group col="4" attrs="{'invisible': [('use_sal','!=',True)]}">
                            <field name="amount_max"/>
                            <field name="amount_invoiced"/>
                            <field name="amount_remaining"/>
                            <field name="amount_sale_to_invoice"/>
                            <field name="amount_sal_to_invoice"/>
                        </group>
                        <group col="4" attrs="{'invisible': [('use_sal','!=',True)]}">
                            <field name="account_analytic_sal_ids" nolabel="1">
                                <tree string="Analytic SAL" editable="top">
                                    <field name="name"/>
                                    <field name="percent_completion"/>
                                    <field name="percent_toinvoice"/>
                                    <field name="amount_toinvoice" readonly="1" sum="Total to Invoice"/>
                                    <field name="amount_invoiced" readonly="1" sum="Total Invoiced"/>
                                    <field name="done"/>
                                    <field name="invoiced"/>
                                    <!--<field name="action_id"/>-->
                                    <!--<field name="action_res_model_id"/>-->
                                    <!--<field name="action_res_id"/>-->
                                </tree>
                            </field>
                        </group>
                    </div>
                </group>
            </field>
        </record>

        <record model="ir.ui.view" id="view_account_invoice_analytic_sal_form">
            <field name="name">account.invoice.form.analytic.sal</field>
            <field name="model">account.invoice</field>
            <field name="inherit_id" ref="account.invoice_form"/>
            <field name="arch" type="xml">
                <xpath expr="//page/field[@name='invoice_line_ids']/tree/field[@name='account_id']" position="after">
                    <field name="account_analytic_sal_id"
                           groups="analytic.group_analytic_accounting"
                           domain="[('account_analytic_id', '=', account_analytic_id)]"/>
                </xpath>
            </field>
        </record>

        <record id="view_account_analytic_sal_filter" model="ir.ui.view">
            <field name="name">account.analytic.sal.filter</field>
            <field name="model">account.analytic.sal</field>
            <field name="arch" type="xml">
                    <search string="Search analytic SAL">
                        <field name="account_analytic_id"/>
                        <field name="name"/>
                        <field name="percent_completion"/>
                        <field name="percent_toinvoice"/>
                        <field name="amount_toinvoice"/>
                        <field name="amount_invoiced"/>
                        <field name="done"/>
                        <field name="invoiced"/>
                        <filter name="to_invoice"
                           string="To invoice"
                           domain="[('invoiced', '=', False)]"/>
                    </search>
            </field>
        </record>
        <record id="view_account_analytic_sal_tree" model="ir.ui.view">
            <field name="name">account.analytic.sal.tree</field>
            <field name="model">account.analytic.sal</field>
            <field name="arch" type="xml">
                <tree colors="red:invoiced==False and done==True;" string="Analytic SAL">
                    <field name="account_analytic_id"/>
                    <field name="name"/>
                    <field name="percent_completion"/>
                    <field name="percent_toinvoice"/>
                    <field name="amount_toinvoice" sum="Total to Invoice"/>
                    <field name="amount_invoiced" sum="Total Invoiced"/>
                    <field name="done"/>
                    <field name="invoiced"/>
                </tree>
            </field>
        </record>
        <record id="view_account_analytic_sal_form" model="ir.ui.view">
            <field name="name">account.analytic.sal.form</field>
            <field name="model">account.analytic.sal</field>
            <field name="arch" type="xml">
                <form string="Analytic SAL">
                    <sheet>
                        <group>
                            <field name="account_analytic_id"/>
                            <field name="name"/>
                        </group>
                        <group col="4">
                            <field name="percent_completion"/>
                            <field name="percent_toinvoice"/>
                            <field name="amount_invoiced" sum="Total Invoiced"/>
                            <field name="amount_toinvoice" sum="Total to Invoice"/>
                            <field name="done"/>
                            <field name="invoiced"/>
                        </group>
                    </sheet>
                </form>
            </field>
        </record>
        <record id="action_account_analytic_sal_line_form" model="ir.actions.act_window">
            <field name="name">Analytic SAL to invoice</field>
            <field name="type">ir.actions.act_window</field>
            <field name="res_model">account.analytic.sal</field>
            <field name="view_type">form</field>
            <field name="view_mode">tree,form</field>
            <field name="context">{"search_default_to_invoice": 1}</field>
            <field name="view_id" ref="view_account_analytic_sal_tree"/>
            <field name="search_view_id" ref="view_account_analytic_sal_filter"/>
        </record>
        <menuitem action="action_account_analytic_sal_line_form" id="account_analytic_sal"
            parent="account.menu_finance_receivables"
            groups="analytic.group_analytic_accounting"
            sequence="100"/>

    </data>
</openerp>
